<!-- This is a generated file. It is highly recommended that you DO NOT edit this file. --><iq:manifest xmlns:iq="http://www.garmin.com/xml/connectiq" version="3">
    <iq:application entry="MeanMaxPowerChartApp" id="b5b612c9-139a-4cf5-ac8a-9974ea783b38" launcherIcon="@Drawables.LauncherIcon" name="@Strings.AppName" type="datafield" version="0.0.0">
        <iq:products>
            <iq:product id="edge1030"/>
            <iq:product id="edge820"/>
            <iq:product id="edge_1000"/>
        </iq:products>
        <iq:permissions>
            <iq:uses-permission id="UserProfile"/>
        </iq:permissions>
        <iq:languages>
            <iq:language>eng</iq:language>
        </iq:languages>
        <iq:barrels/>
    </iq:application>
</iq:manifest>
